spyglass_mcp/__init__.py
spyglass_mcp/main.py
spyglass_mcp-0.1.0.dist-info/METADATA
spyglass_mcp-0.1.0.dist-info/WHEEL
spyglass_mcp-0.1.0.dist-info/entry_points.txt
spyglass_mcp-0.1.0.dist-info/licenses/LICENSE
spyglass_mcp-0.1.0.dist-info/RECORD
