Metadata-Version: 2.4
Name: spyglass-mcp
Version: 0.1.0
Summary: FastMCP server for Spyglass AI agent
Project-URL: Homepage, https://spyglass-ai.com
Project-URL: Repository, https://github.com/spyglass-ai/spyglass-mcp
Project-URL: Bug Reports, https://github.com/spyglass-ai/spyglass-mcp/issues
Author-email: Spyglass AI Team <team@spyglass-ai.com>
License-Expression: MIT
License-File: LICENSE
Keywords: agent,ai,mcp,model-context-protocol,observability,opentelemetry,spyglass
Classifier: Development Status :: 3 - Alpha
Classifier: Intended Audience :: Developers
Classifier: License :: OSI Approved :: MIT License
Classifier: Operating System :: OS Independent
Classifier: Programming Language :: Python :: 3
Classifier: Programming Language :: Python :: 3.13
Classifier: Topic :: Software Development :: Libraries :: Python Modules
Classifier: Topic :: System :: Monitoring
Requires-Python: >=3.11
Requires-Dist: fastmcp>=0.1.0
Requires-Dist: httpx>=0.27.0
Requires-Dist: python-dotenv>=1.0.0
Provides-Extra: dev
Requires-Dist: pytest-asyncio>=0.21.0; extra == 'dev'
Requires-Dist: pytest-mock>=3.10.0; extra == 'dev'
Requires-Dist: pytest>=7.0.0; extra == 'dev'
Requires-Dist: respx>=0.20.0; extra == 'dev'
Provides-Extra: test
Requires-Dist: pytest-asyncio>=0.21.0; extra == 'test'
Requires-Dist: pytest-mock>=3.10.0; extra == 'test'
Requires-Dist: pytest>=7.0.0; extra == 'test'
Requires-Dist: respx>=0.20.0; extra == 'test'
